jaxglm/__init__.py
jaxglm/__version__.py
jaxglm/families.py
jaxglm/links.py
jaxglm/model.py
jaxglm/results.py
jaxglm/utils.py
jaxglm-0.1.1.dist-info/WHEEL
jaxglm-0.1.1.dist-info/METADATA
jaxglm-0.1.1.dist-info/RECORD
